{
    "patches": [
        {
            "label": "2025-11-06_13-12-20",
            "content": "@@ -650,37 +650,36 @@\n ef chamar(self, \n-index\n+vaga\n :int):%0A        i\n@@ -684,25 +684,24 @@\n  if \n-index\n+vaga \n %3C 0 or \n-index\n+vaga\n  %3E= \n@@ -801,29 +801,28 @@\n self.caixas%5B\n-index\n+vaga\n %5D is not Non\n@@ -965,820 +965,53 @@\n xas%5B\n-index%5D = self.espera%5B0%5D  %0A        del self.espera%0A%0A    def finalizar(self, index:int):%0A        self.caixas%5Bindex%5D=None%0A        if index %3C 0 or index %3E= len(self.caixas):%0A            print(%22fail: caixa inexistente%22)%0A            return%0A        if self.caixas%5Bindex%5D is None:%0A            print(%22fail: caixa vazio%22)%0A            return%0A        %0A    def sair(self, nome: str) -%3E Person %7C None:%0A        for i, pessoa in enumerate(self.espera):%0A            if pessoa.nome == nome:%0A                pessoa_removida = self.espera%5Bi%5D%0A                del self.espera%5Bi%5D%0A            return pessoa_removida  %0A        return None  %0A%0A%0Adef __str__(self):%0A    caixas = %22, %22.join(%5Bstr(x) if x else %22----%22 for x in self.caixas%5D)%0A    espera = %22, %22.join(%5Bstr(x) for x in self.espera%5D)%0A    return f%22Caixas: %7Bcaixas%7D%5CnEspera: %7Bespera%7D%22%0A%0A    \n+vaga%5D = self.espera%5B0%5D  %0A        del self.espera%0A\n",
            "lines": "36"
        },
        {
            "label": "2025-11-07_14-19-54",
            "content": "class Person:\n    def __init__(self, nome:str) -> None:\n        self.__nome = nome\n\n    def getNome(self):\n        return self.__nome\n\n    def setNome(self, nome:str):\n        if nome.strip():\n            self.__nome = nome\n        else:\n            self.__nome = \"Ningu\u00e9m\"\n\n    def __str__(self) -> str:\n        return f\"Nome: {self.__nome}\"\n\nclass Budega:\n    def __init__(self,num_caixas:int) -> None:\n        self.caixas: list[Person | None]= []\n        for _ in range(num_caixas):\n            self.caixas.append(None)\n            self.espera: list[Person]=[]\n    \n    def entrar (self, person :Person):\n        self.espera.append(person)\n\n    def chamar(self, index:int):\n        if index< 0 or index >= len(self.caixas):\n            print(\"fail: caixa inexistente\")\n            return\n        if self.caixas[index] is not None:\n            print(\"fail: caixa ocupado\")\n        if len (self.espera )== 0:\n            print(\" fail: sem clientes\")\n        self.caixas[index] = self.espera[0]  \n        del self.espera\n\n    def finalizar(self, index:int):\n        self.caixas[index]=None\n        if index < 0 or index >= len(self.caixas):\n            print(\"fail: caixa inexistente\")\n            return\n        if self.caixas[index] is None:\n            print(\"fail: caixa vazio\")\n            return\n        \n    def sair(self, nome: str) -> Person | None:\n        for i, pessoa in enumerate(self.espera):\n            if pessoa.nome == nome:\n                pessoa_removida = self.espera[i]\n                del self.espera[i]\n            return pessoa_removida  \n        return None  \n\n\ndef __str__(self):\n    caixas = \", \".join([str(x) if x else \"----\" for x in self.caixas])\n    espera = \", \".join([str(x) for x in self.espera])\n    return f\"Caixas: {caixas}\\nEspera: {espera}\"\n\n    ",
            "lines": "61"
        }
    ]
}